[{"Name":"toyota corona mark ii","Miles_per_Gallon":24.0,"Cylinders":4,"Displacement":113.0,"Horsepower":95.0,"Weight_in_lbs":2372,"Acceleration":15.0,"Year":"1970-01-01T00:00:00","Origin":"Japan"},{"Name":"datsun pl510","Miles_per_Gallon":27.0,"Cylinders":4,"Displacement":97.0,"Horsepower":88.0,"Weight_in_lbs":2130,"Acceleration":14.5,"Year":"1970-01-01T00:00:00","Origin":"Japan"},{"Name":"datsun pl510","Miles_per_Gallon":27.0,"Cylinders":4,"Displacement":97.0,"Horsepower":88.0,"Weight_in_lbs":2130,"Acceleration":14.5,"Year":"1971-01-01T00:00:00","Origin":"Japan"},{"Name":"toyota corona","Miles_per_Gallon":25.0,"Cylinders":4,"Displacement":113.0,"Horsepower":95.0,"Weight_in_lbs":2228,"Acceleration":14.0,"Year":"1971-01-01T00:00:00","Origin":"Japan"},{"Name":"toyota corolla 1200","Miles_per_Gallon":31.0,"Cylinders":4,"Displacement":71.0,"Horsepower":65.0,"Weight_in_lbs":1773,"Acceleration":19.0,"Year":"1971-01-01T00:00:00","Origin":"Japan"},{"Name":"datsun 1200","Miles_per_Gallon":35.0,"Cylinders":4,"Displacement":72.0,"Horsepower":69.0,"Weight_in_lbs":1613,"Acceleration":18.0,"Year":"1971-01-01T00:00:00","Origin":"Japan"},{"Name":"toyota corona hardtop","Miles_per_Gallon":24.0,"Cylinders":4,"Displacement":113.0,"Horsepower":95.0,"Weight_in_lbs":2278,"Acceleration":15.5,"Year":"1972-01-01T00:00:00","Origin":"Japan"},{"Name":"mazda rx2 coupe","Miles_per_Gallon":19.0,"Cylinders":3,"Displacement":70.0,"Horsepower":97.0,"Weight_in_lbs":2330,"Acceleration":13.5,"Year":"1972-01-01T00:00:00","Origin":"Japan"},{"Name":"datsun 510 (sw)","Miles_per_Gallon":28.0,"Cylinders":4,"Displacement":97.0,"Horsepower":92.0,"Weight_in_lbs":2288,"Acceleration":17.0,"Year":"1972-01-01T00:00:00","Origin":"Japan"},{"Name":"toyouta corona mark ii (sw)","Miles_per_Gallon":23.0,"Cylinders":4,"Displacement":120.0,"Horsepower":97.0,"Weight_in_lbs":2506,"Acceleration":14.5,"Year":"1972-01-01T00:00:00","Origin":"Japan"},{"Name":"toyota corolla 1600 (sw)","Miles_per_Gallon":27.0,"Cylinders":4,"Displacement":97.0,"Horsepower":88.0,"Weight_in_lbs":2100,"Acceleration":16.5,"Year":"1972-01-01T00:00:00","Origin":"Japan"},{"Name":"toyota carina","Miles_per_Gallon":20.0,"Cylinders":4,"Displacement":97.0,"Horsepower":88.0,"Weight_in_lbs":2279,"Acceleration":19.0,"Year":"1973-01-01T00:00:00","Origin":"Japan"},{"Name":"datsun 610","Miles_per_Gallon":22.0,"Cylinders":4,"Displacement":108.0,"Horsepower":94.0,"Weight_in_lbs":2379,"Acceleration":16.5,"Year":"1973-01-01T00:00:00","Origin":"Japan"},{"Name":"maxda rx3","Miles_per_Gallon":18.0,"Cylinders":3,"Displacement":70.0,"Horsepower":90.0,"Weight_in_lbs":2124,"Acceleration":13.5,"Year":"1973-01-01T00:00:00","Origin":"Japan"},{"Name":"toyota mark ii","Miles_per_Gallon":20.0,"Cylinders":6,"Displacement":156.0,"Horsepower":122.0,"Weight_in_lbs":2807,"Acceleration":13.5,"Year":"1973-01-01T00:00:00","Origin":"Japan"},{"Name":"datsun b210","Miles_per_Gallon":31.0,"Cylinders":4,"Displacement":79.0,"Horsepower":67.0,"Weight_in_lbs":1950,"Acceleration":19.0,"Year":"1974-01-01T00:00:00","Origin":"Japan"},{"Name":"toyota corolla 1200","Miles_per_Gallon":32.0,"Cylinders":4,"Displacement":71.0,"Horsepower":65.0,"Weight_in_lbs":1836,"Acceleration":21.0,"Year":"1974-01-01T00:00:00","Origin":"Japan"},{"Name":"toyota corona","Miles_per_Gallon":31.0,"Cylinders":4,"Displacement":76.0,"Horsepower":52.0,"Weight_in_lbs":1649,"Acceleration":16.5,"Year":"1974-01-01T00:00:00","Origin":"Japan"},{"Name":"datsun 710","Miles_per_Gallon":32.0,"Cylinders":4,"Displacement":83.0,"Horsepower":61.0,"Weight_in_lbs":2003,"Acceleration":19.0,"Year":"1974-01-01T00:00:00","Origin":"Japan"},{"Name":"honda civic","Miles_per_Gallon":24.0,"Cylinders":4,"Displacement":120.0,"Horsepower":97.0,"Weight_in_lbs":2489,"Acceleration":15.0,"Year":"1974-01-01T00:00:00","Origin":"Japan"},{"Name":"subaru","Miles_per_Gallon":26.0,"Cylinders":4,"Displacement":108.0,"Horsepower":93.0,"Weight_in_lbs":2391,"Acceleration":15.5,"Year":"1974-01-01T00:00:00","Origin":"Japan"},{"Name":"toyota corolla","Miles_per_Gallon":29.0,"Cylinders":4,"Displacement":97.0,"Horsepower":75.0,"Weight_in_lbs":2171,"Acceleration":16.0,"Year":"1975-01-01T00:00:00","Origin":"Japan"},{"Name":"toyota corona","Miles_per_Gallon":24.0,"Cylinders":4,"Displacement":134.0,"Horsepower":96.0,"Weight_in_lbs":2702,"Acceleration":13.5,"Year":"1975-01-01T00:00:00","Origin":"Japan"},{"Name":"datsun 710","Miles_per_Gallon":24.0,"Cylinders":4,"Displacement":119.0,"Horsepower":97.0,"Weight_in_lbs":2545,"Acceleration":17.0,"Year":"1975-01-01T00:00:00","Origin":"Japan"},{"Name":"honda civic cvcc","Miles_per_Gallon":33.0,"Cylinders":4,"Displacement":91.0,"Horsepower":53.0,"Weight_in_lbs":1795,"Acceleration":17.5,"Year":"1975-01-01T00:00:00","Origin":"Japan"},{"Name":"honda civic","Miles_per_Gallon":33.0,"Cylinders":4,"Displacement":91.0,"Horsepower":53.0,"Weight_in_lbs":1795,"Acceleration":17.4,"Year":"1976-01-01T00:00:00","Origin":"Japan"},{"Name":"datsun b-210","Miles_per_Gallon":32.0,"Cylinders":4,"Displacement":85.0,"Horsepower":70.0,"Weight_in_lbs":1990,"Acceleration":17.0,"Year":"1976-01-01T00:00:00","Origin":"Japan"},{"Name":"toyota corolla","Miles_per_Gallon":28.0,"Cylinders":4,"Displacement":97.0,"Horsepower":75.0,"Weight_in_lbs":2155,"Acceleration":16.4,"Year":"1976-01-01T00:00:00","Origin":"Japan"},{"Name":"toyota mark ii","Miles_per_Gallon":19.0,"Cylinders":6,"Displacement":156.0,"Horsepower":108.0,"Weight_in_lbs":2930,"Acceleration":15.5,"Year":"1976-01-01T00:00:00","Origin":"Japan"},{"Name":"honda Accelerationord cvcc","Miles_per_Gallon":31.5,"Cylinders":4,"Displacement":98.0,"Horsepower":68.0,"Weight_in_lbs":2045,"Acceleration":18.5,"Year":"1977-01-01T00:00:00","Origin":"Japan"},{"Name":"datsun f-10 hatchback","Miles_per_Gallon":33.5,"Cylinders":4,"Displacement":85.0,"Horsepower":70.0,"Weight_in_lbs":1945,"Acceleration":16.8,"Year":"1977-01-01T00:00:00","Origin":"Japan"},{"Name":"toyota corolla liftback","Miles_per_Gallon":26.0,"Cylinders":4,"Displacement":97.0,"Horsepower":75.0,"Weight_in_lbs":2265,"Acceleration":18.2,"Year":"1977-01-01T00:00:00","Origin":"Japan"},{"Name":"subaru dl","Miles_per_Gallon":30.0,"Cylinders":4,"Displacement":97.0,"Horsepower":67.0,"Weight_in_lbs":1985,"Acceleration":16.4,"Year":"1977-01-01T00:00:00","Origin":"Japan"},{"Name":"datsun 810","Miles_per_Gallon":22.0,"Cylinders":6,"Displacement":146.0,"Horsepower":97.0,"Weight_in_lbs":2815,"Acceleration":14.5,"Year":"1977-01-01T00:00:00","Origin":"Japan"},{"Name":"mazda rx-4","Miles_per_Gallon":21.5,"Cylinders":3,"Displacement":80.0,"Horsepower":110.0,"Weight_in_lbs":2720,"Acceleration":13.5,"Year":"1977-01-01T00:00:00","Origin":"Japan"},{"Name":"mazda glc deluxe","Miles_per_Gallon":32.8,"Cylinders":4,"Displacement":78.0,"Horsepower":52.0,"Weight_in_lbs":1985,"Acceleration":19.4,"Year":"1978-01-01T00:00:00","Origin":"Japan"},{"Name":"datsun b210 gx","Miles_per_Gallon":39.4,"Cylinders":4,"Displacement":85.0,"Horsepower":70.0,"Weight_in_lbs":2070,"Acceleration":18.6,"Year":"1978-01-01T00:00:00","Origin":"Japan"},{"Name":"honda civic cvcc","Miles_per_Gallon":36.1,"Cylinders":4,"Displacement":91.0,"Horsepower":60.0,"Weight_in_lbs":1800,"Acceleration":16.4,"Year":"1978-01-01T00:00:00","Origin":"Japan"},{"Name":"toyota corona","Miles_per_Gallon":27.5,"Cylinders":4,"Displacement":134.0,"Horsepower":95.0,"Weight_in_lbs":2560,"Acceleration":14.2,"Year":"1978-01-01T00:00:00","Origin":"Japan"},{"Name":"datsun 510","Miles_per_Gallon":27.2,"Cylinders":4,"Displacement":119.0,"Horsepower":97.0,"Weight_in_lbs":2300,"Acceleration":14.7,"Year":"1978-01-01T00:00:00","Origin":"Japan"},{"Name":"toyota celica gt liftback","Miles_per_Gallon":21.1,"Cylinders":4,"Displacement":134.0,"Horsepower":95.0,"Weight_in_lbs":2515,"Acceleration":14.8,"Year":"1978-01-01T00:00:00","Origin":"Japan"},{"Name":"datsun 200-sx","Miles_per_Gallon":23.9,"Cylinders":4,"Displacement":119.0,"Horsepower":97.0,"Weight_in_lbs":2405,"Acceleration":14.9,"Year":"1978-01-01T00:00:00","Origin":"Japan"},{"Name":"honda Accelerationord lx","Miles_per_Gallon":29.5,"Cylinders":4,"Displacement":98.0,"Horsepower":68.0,"Weight_in_lbs":2135,"Acceleration":16.6,"Year":"1978-01-01T00:00:00","Origin":"Japan"},{"Name":"maxda glc deluxe","Miles_per_Gallon":34.1,"Cylinders":4,"Displacement":86.0,"Horsepower":65.0,"Weight_in_lbs":1975,"Acceleration":15.2,"Year":"1979-01-01T00:00:00","Origin":"Japan"},{"Name":"datsun 210","Miles_per_Gallon":31.8,"Cylinders":4,"Displacement":85.0,"Horsepower":65.0,"Weight_in_lbs":2020,"Acceleration":19.2,"Year":"1979-01-01T00:00:00","Origin":"Japan"},{"Name":"toyota corolla tercel","Miles_per_Gallon":38.1,"Cylinders":4,"Displacement":89.0,"Horsepower":60.0,"Weight_in_lbs":1968,"Acceleration":18.8,"Year":"1980-01-01T00:00:00","Origin":"Japan"},{"Name":"datsun 310","Miles_per_Gallon":37.2,"Cylinders":4,"Displacement":86.0,"Horsepower":65.0,"Weight_in_lbs":2019,"Acceleration":16.4,"Year":"1980-01-01T00:00:00","Origin":"Japan"},{"Name":"toyota corona liftback","Miles_per_Gallon":29.8,"Cylinders":4,"Displacement":134.0,"Horsepower":90.0,"Weight_in_lbs":2711,"Acceleration":15.5,"Year":"1980-01-01T00:00:00","Origin":"Japan"},{"Name":"mazda 626","Miles_per_Gallon":31.3,"Cylinders":4,"Displacement":120.0,"Horsepower":75.0,"Weight_in_lbs":2542,"Acceleration":17.5,"Year":"1980-01-01T00:00:00","Origin":"Japan"},{"Name":"datsun 510 hatchback","Miles_per_Gallon":37.0,"Cylinders":4,"Displacement":119.0,"Horsepower":92.0,"Weight_in_lbs":2434,"Acceleration":15.0,"Year":"1980-01-01T00:00:00","Origin":"Japan"},{"Name":"toyota corolla","Miles_per_Gallon":32.2,"Cylinders":4,"Displacement":108.0,"Horsepower":75.0,"Weight_in_lbs":2265,"Acceleration":15.2,"Year":"1980-01-01T00:00:00","Origin":"Japan"},{"Name":"mazda glc","Miles_per_Gallon":46.6,"Cylinders":4,"Displacement":86.0,"Horsepower":65.0,"Weight_in_lbs":2110,"Acceleration":17.9,"Year":"1980-01-01T00:00:00","Origin":"Japan"},{"Name":"datsun 210","Miles_per_Gallon":40.8,"Cylinders":4,"Displacement":85.0,"Horsepower":65.0,"Weight_in_lbs":2110,"Acceleration":19.2,"Year":"1980-01-01T00:00:00","Origin":"Japan"},{"Name":"honda civic 1500 gl","Miles_per_Gallon":44.6,"Cylinders":4,"Displacement":91.0,"Horsepower":67.0,"Weight_in_lbs":1850,"Acceleration":13.8,"Year":"1980-01-01T00:00:00","Origin":"Japan"},{"Name":"subaru dl","Miles_per_Gallon":33.8,"Cylinders":4,"Displacement":97.0,"Horsepower":67.0,"Weight_in_lbs":2145,"Acceleration":18.0,"Year":"1980-01-01T00:00:00","Origin":"Japan"},{"Name":"datsun 280-zx","Miles_per_Gallon":32.7,"Cylinders":6,"Displacement":168.0,"Horsepower":132.0,"Weight_in_lbs":2910,"Acceleration":11.4,"Year":"1980-01-01T00:00:00","Origin":"Japan"},{"Name":"mazda rx-7 gs","Miles_per_Gallon":23.7,"Cylinders":3,"Displacement":70.0,"Horsepower":100.0,"Weight_in_lbs":2420,"Acceleration":12.5,"Year":"1980-01-01T00:00:00","Origin":"Japan"},{"Name":"honda Accelerationord","Miles_per_Gallon":32.4,"Cylinders":4,"Displacement":107.0,"Horsepower":72.0,"Weight_in_lbs":2290,"Acceleration":17.0,"Year":"1980-01-01T00:00:00","Origin":"Japan"},{"Name":"toyota starlet","Miles_per_Gallon":39.1,"Cylinders":4,"Displacement":79.0,"Horsepower":58.0,"Weight_in_lbs":1755,"Acceleration":16.9,"Year":"1982-01-01T00:00:00","Origin":"Japan"},{"Name":"honda civic 1300","Miles_per_Gallon":35.1,"Cylinders":4,"Displacement":81.0,"Horsepower":60.0,"Weight_in_lbs":1760,"Acceleration":16.1,"Year":"1982-01-01T00:00:00","Origin":"Japan"},{"Name":"subaru","Miles_per_Gallon":32.3,"Cylinders":4,"Displacement":97.0,"Horsepower":67.0,"Weight_in_lbs":2065,"Acceleration":17.8,"Year":"1982-01-01T00:00:00","Origin":"Japan"},{"Name":"datsun 210","Miles_per_Gallon":37.0,"Cylinders":4,"Displacement":85.0,"Horsepower":65.0,"Weight_in_lbs":1975,"Acceleration":19.4,"Year":"1982-01-01T00:00:00","Origin":"Japan"},{"Name":"toyota tercel","Miles_per_Gallon":37.7,"Cylinders":4,"Displacement":89.0,"Horsepower":62.0,"Weight_in_lbs":2050,"Acceleration":17.3,"Year":"1982-01-01T00:00:00","Origin":"Japan"},{"Name":"mazda glc 4","Miles_per_Gallon":34.1,"Cylinders":4,"Displacement":91.0,"Horsepower":68.0,"Weight_in_lbs":1985,"Acceleration":16.0,"Year":"1982-01-01T00:00:00","Origin":"Japan"},{"Name":"honda prelude","Miles_per_Gallon":33.7,"Cylinders":4,"Displacement":107.0,"Horsepower":75.0,"Weight_in_lbs":2210,"Acceleration":14.4,"Year":"1982-01-01T00:00:00","Origin":"Japan"},{"Name":"toyota corolla","Miles_per_Gallon":32.4,"Cylinders":4,"Displacement":108.0,"Horsepower":75.0,"Weight_in_lbs":2350,"Acceleration":16.8,"Year":"1982-01-01T00:00:00","Origin":"Japan"},{"Name":"datsun 200sx","Miles_per_Gallon":32.9,"Cylinders":4,"Displacement":119.0,"Horsepower":100.0,"Weight_in_lbs":2615,"Acceleration":14.8,"Year":"1982-01-01T00:00:00","Origin":"Japan"},{"Name":"mazda 626","Miles_per_Gallon":31.6,"Cylinders":4,"Displacement":120.0,"Horsepower":74.0,"Weight_in_lbs":2635,"Acceleration":18.3,"Year":"1982-01-01T00:00:00","Origin":"Japan"},{"Name":"toyota cressida","Miles_per_Gallon":25.4,"Cylinders":6,"Displacement":168.0,"Horsepower":116.0,"Weight_in_lbs":2900,"Acceleration":12.6,"Year":"1982-01-01T00:00:00","Origin":"Japan"},{"Name":"datsun 810 maxima","Miles_per_Gallon":24.2,"Cylinders":6,"Displacement":146.0,"Horsepower":120.0,"Weight_in_lbs":2930,"Acceleration":13.8,"Year":"1982-01-01T00:00:00","Origin":"Japan"},{"Name":"mazda glc custom l","Miles_per_Gallon":37.0,"Cylinders":4,"Displacement":91.0,"Horsepower":68.0,"Weight_in_lbs":2025,"Acceleration":18.2,"Year":"1982-01-01T00:00:00","Origin":"Japan"},{"Name":"mazda glc custom","Miles_per_Gallon":31.0,"Cylinders":4,"Displacement":91.0,"Horsepower":68.0,"Weight_in_lbs":1970,"Acceleration":17.6,"Year":"1982-01-01T00:00:00","Origin":"Japan"},{"Name":"nissan stanza xe","Miles_per_Gallon":36.0,"Cylinders":4,"Displacement":120.0,"Horsepower":88.0,"Weight_in_lbs":2160,"Acceleration":14.5,"Year":"1982-01-01T00:00:00","Origin":"Japan"},{"Name":"honda Accelerationord","Miles_per_Gallon":36.0,"Cylinders":4,"Displacement":107.0,"Horsepower":75.0,"Weight_in_lbs":2205,"Acceleration":14.5,"Year":"1982-01-01T00:00:00","Origin":"Japan"},{"Name":"toyota corolla","Miles_per_Gallon":34.0,"Cylinders":4,"Displacement":108.0,"Horsepower":70.0,"Weight_in_lbs":2245,"Acceleration":16.9,"Year":"1982-01-01T00:00:00","Origin":"Japan"},{"Name":"honda civic","Miles_per_Gallon":38.0,"Cylinders":4,"Displacement":91.0,"Horsepower":67.0,"Weight_in_lbs":1965,"Acceleration":15.0,"Year":"1982-01-01T00:00:00","Origin":"Japan"},{"Name":"honda civic (auto)","Miles_per_Gallon":32.0,"Cylinders":4,"Displacement":91.0,"Horsepower":67.0,"Weight_in_lbs":1965,"Acceleration":15.7,"Year":"1982-01-01T00:00:00","Origin":"Japan"},{"Name":"datsun 310 gx","Miles_per_Gallon":38.0,"Cylinders":4,"Displacement":91.0,"Horsepower":67.0,"Weight_in_lbs":1995,"Acceleration":16.2,"Year":"1982-01-01T00:00:00","Origin":"Japan"},{"Name":"toyota celica gt","Miles_per_Gallon":32.0,"Cylinders":4,"Displacement":144.0,"Horsepower":96.0,"Weight_in_lbs":2665,"Acceleration":13.9,"Year":"1982-01-01T00:00:00","Origin":"Japan"}]